permit_fastmcp/__init__.py
permit_fastmcp/logger_config.py
permit_fastmcp/run_example_server.py
permit_fastmcp/example_server/__init__.py
permit_fastmcp/example_server/example.py
permit_fastmcp/middleware/__init__.py
permit_fastmcp/middleware/config.py
permit_fastmcp/middleware/middleware.py
permit_fastmcp/middleware/utils.py
permit_fastmcp-0.1.2.dist-info/licenses/LICENSE
permit_fastmcp-0.1.2.dist-info/METADATA
permit_fastmcp-0.1.2.dist-info/WHEEL
permit_fastmcp-0.1.2.dist-info/top_level.txt
permit_fastmcp-0.1.2.dist-info/RECORD
