Metadata-Version: 2.4
Name: permit-fastmcp
Version: 0.1.2
Summary: Permit.io authorization middleware for FastMCP servers.
Author-email: Or Weis <or@permit.io>
License-Expression: Apache-2.0
Classifier: Programming Language :: Python :: 3
Classifier: Operating System :: OS Independent
Requires-Python: >=3.11
License-File: LICENSE
Requires-Dist: fastmcp>=2.10.1
Requires-Dist: permit>=2.7.5
Requires-Dist: pydantic>=2.11.7
Requires-Dist: pydantic-settings>=2.0.0
Requires-Dist: starlette>=0.47.1
Requires-Dist: pyjwt>=2.8.0
Provides-Extra: dev
Requires-Dist: black>=23.0.0; extra == "dev"
Dynamic: license-file
